pearlib/__init__.py
pearlib/apply_nonlinearity.py
pearlib/calculate_all_output.py
pearlib/calculate_output.py
pearlib/create_image.py
pearlib/create_image_from_lines.py
pearlib/draw_line.py
pearlib/example.py
pearlib/get_all_lines.py
pearlib/get_color_for_layeridx.py
pearlib/get_lines_from_layer_output.py
pearlib/layer.py
pearlib/line.py
pearlib/network.py
pearlib/reader.py
pearlib/save_image.py
pearlib/sigmoid.py
pearlib-1.0.dist-info/DESCRIPTION.rst
pearlib-1.0.dist-info/METADATA
pearlib-1.0.dist-info/RECORD
pearlib-1.0.dist-info/WHEEL
pearlib-1.0.dist-info/metadata.json
pearlib-1.0.dist-info/top_level.txt
