Metadata-Version: 2.0
Name: pearlib
Version: 1.0
Summary: The library that makes neural networks appear
Home-page: https://github.com/danimano/TRP
Author: Candice Bentéjac, Anna Csörgő and Dániel Hajtó
Author-email: candice.bentejac@etu.u-bordeaux.fr
License: BSD-3-Clause
Keywords: tensorflow neural networks visualization
Platform: UNKNOWN
Classifier: Development Status :: 3 - Alpha
Classifier: License :: OSI Approved :: BSD License
Classifier: Natural Language :: English
Classifier: Programming Language :: Python :: 3.6
Classifier: Topic :: Scientific/Engineering :: Visualization
Classifier: Framework :: IDLE
Requires-Python: >=3
Requires-Dist: numpy
Requires-Dist: matplotlib
Requires-Dist: Pillow
Requires-Dist: tensorflow
Requires-Dist: webcolors
